operatorcourier/__init__.py
operatorcourier/api.py
operatorcourier/build.py
operatorcourier/cli.py
operatorcourier/const_io.py
operatorcourier/errors.py
operatorcourier/flatten.py
operatorcourier/format.py
operatorcourier/identify.py
operatorcourier/manifest_parser.py
operatorcourier/nest.py
operatorcourier/push.py
operatorcourier/validate.py
operatorcourier/verified_manifest.py
operator_courier-2.1.11.dist-info/LICENSE
operator_courier-2.1.11.dist-info/METADATA
operator_courier-2.1.11.dist-info/WHEEL
operator_courier-2.1.11.dist-info/entry_points.txt
operator_courier-2.1.11.dist-info/top_level.txt
operator_courier-2.1.11.dist-info/RECORD
