Metadata-Version: 2.1
Name: operator-courier
Version: 2.1.11
Summary: Build, verify and push operators
Home-page: https://github.com/operator-framework/operator-courier
Author: AOS Marketplace
Author-email: aos-marketplace@redhat.com
License: Apache License 2.0
Keywords: operator,courier
Platform: UNKNOWN
Classifier: Programming Language :: Python :: 3.6
Classifier: Programming Language :: Python :: 3.7
Requires-Python: >=3.6, <4
Requires-Dist: pyyaml
Requires-Dist: requests
Requires-Dist: validators
Requires-Dist: semver
Provides-Extra: test
Requires-Dist: pytest ; extra == 'test'
Requires-Dist: pytest-cov ; extra == 'test'
Requires-Dist: testfixtures ; extra == 'test'
